click_toolbelt/__init__.py
click_toolbelt/channels.py
click_toolbelt/common.py
click_toolbelt/compat.py
click_toolbelt/config.py
click_toolbelt/constants.py
click_toolbelt/info.py
click_toolbelt/login.py
click_toolbelt/toolbelt.py
click_toolbelt/upload.py
click_toolbelt/tests/__init__.py
click_toolbelt/tests/test_channels.py
click_toolbelt/tests/test_common.py
click_toolbelt/tests/test_config.py
click_toolbelt/tests/test_info.py
click_toolbelt/tests/test_login.py
click_toolbelt/tests/test_toolbelt.py
click_toolbelt/tests/test_upload.py
click_toolbelt-0.5.1.dist-info/DESCRIPTION.rst
click_toolbelt-0.5.1.dist-info/METADATA
click_toolbelt-0.5.1.dist-info/RECORD
click_toolbelt-0.5.1.dist-info/WHEEL
click_toolbelt-0.5.1.dist-info/entry_points.txt
click_toolbelt-0.5.1.dist-info/metadata.json
click_toolbelt-0.5.1.dist-info/namespace_packages.txt
click_toolbelt-0.5.1.dist-info/top_level.txt
storeapi/__init__.py
storeapi/_login.py
storeapi/_upload.py
storeapi/channels.py
storeapi/common.py
storeapi/compat.py
storeapi/constants.py
storeapi/info.py
storeapi/tests/__init__.py
storeapi/tests/test_channels.py
storeapi/tests/test_common.py
storeapi/tests/test_info.py
storeapi/tests/test_login.py
storeapi/tests/test_upload.py
