Metadata-Version: 2.0
Name: click-toolbelt
Version: 0.5.1
Summary: Click App Toolbelt
Home-page: https://launchpad.net/click-toolbelt
Author: Ricardo Kirkner
Author-email: ricardo.kirkner@canonical.com
License: UNKNOWN
Download-URL: https://launchpad.net/click-toolbelt
Platform: Any
Classifier: Development Status :: 4 - Beta
Classifier: License :: OSI Approved :: GNU General Public License v3 (GPLv3)
Classifier: Programming Language :: Python
Classifier: Programming Language :: Python :: 2
Classifier: Programming Language :: Python :: 2.7
Classifier: Programming Language :: Python :: 3
Classifier: Programming Language :: Python :: 3.3
Classifier: Intended Audience :: Developers
Classifier: Environment :: Console
Requires-Dist: cliff
Requires-Dist: pyxdg
Requires-Dist: requests
Requires-Dist: requests-oauthlib
Requires-Dist: ssoclient
